neofox/MHC_predictors/MixMHCpred/__init__.py
neofox/MHC_predictors/MixMHCpred/mixmhc2pred.py
neofox/MHC_predictors/MixMHCpred/mixmhcpred.py
neofox/MHC_predictors/__init__.py
neofox/MHC_predictors/netmhcpan/__init__.py
neofox/MHC_predictors/netmhcpan/combine_netmhcIIpan_pred_multiple_binders.py
neofox/MHC_predictors/netmhcpan/combine_netmhcpan_pred_multiple_binders.py
neofox/MHC_predictors/netmhcpan/netmhcIIpan_prediction.py
neofox/MHC_predictors/netmhcpan/netmhcpan_prediction.py
neofox/MHC_predictors/prime.py
neofox/__init__.py
neofox/annotation_resources/__init__.py
neofox/annotation_resources/uniprot/__init__.py
neofox/annotation_resources/uniprot/uniprot.py
neofox/annotator/__init__.py
neofox/annotator/abstract_annotator.py
neofox/annotator/neoantigen_annotator.py
neofox/annotator/neoantigen_mhc_binding_annotator.py
neofox/annotator/neoepitope_annotator.py
neofox/annotator/neoepitope_mhc_binding_annotator.py
neofox/annotator.py
neofox/command_line.py
neofox/exceptions.py
neofox/expression_imputation/__init__.py
neofox/expression_imputation/expression_imputation.py
neofox/expression_imputation/tcga_cohort_code.tab
neofox/expression_imputation/tcga_exp_summary_modified.tab.gz
neofox/expression_imputation/tcga_exp_summary_modified.tab.gz.tbi
neofox/helpers/__init__.py
neofox/helpers/blastp_runner.py
neofox/helpers/epitope_helper.py
neofox/helpers/intermediate_files.py
neofox/helpers/mhc_helper.py
neofox/helpers/runner.py
neofox/helpers/temp.fasta
neofox/model/Makefile
neofox/model/README.md
neofox/model/__init__.py
neofox/model/conversion.py
neofox/model/factories.py
neofox/model/mhc_parser.py
neofox/model/models.md
neofox/model/models_template.tmpl
neofox/model/neoantigen.proto
neofox/model/neoantigen.py
neofox/model/validation.py
neofox/neofox.py
neofox/neofox_epitope.py
neofox/published_features/__init__.py
neofox/published_features/differential_binding/__init__.py
neofox/published_features/differential_binding/amplitude.py
neofox-1.2.3.dist-info/LICENSE
neofox-1.2.3.dist-info/METADATA
neofox-1.2.3.dist-info/WHEEL
neofox-1.2.3.dist-info/entry_points.txt
neofox-1.2.3.dist-info/RECORD
