Metadata-Version: 2.1
Name: neofox
Version: 1.2.3
Summary: NEOantigen Feature tOolboX
License: GPLv3
Author: TRON - Translational Oncology at the University Medical Center
Requires-Python: >=3.11,<3.12
Classifier: License :: Other/Proprietary License
Classifier: Programming Language :: Python :: 3
Classifier: Programming Language :: Python :: 3.11
Requires-Dist: betterproto (>=1.2.5,<1.3.0)
Requires-Dist: biopython (>1.80)
Requires-Dist: cython (>3)
Requires-Dist: dask (>=2024.0.0,<=2024.6.2)
Requires-Dist: distributed (>=2024.0.0,<=2024.6.2)
Requires-Dist: faker (>=13.13.0,<13.14.0)
Requires-Dist: logzero (>=1.5.0)
Requires-Dist: mock (>=4.0.3,<4.1.0)
Requires-Dist: numpy (>=1.24,<1.27)
Requires-Dist: pandas (>=2.1,<2.3)
Requires-Dist: pysam (>0.20)
Requires-Dist: python-dotenv (>=0.12.0,<0.13.0)
Requires-Dist: scipy (>=1.10.0)
Requires-Dist: tornado (==6.4.2)
Requires-Dist: xmltodict (>=0.12.0,<0.13.0)
